wawpybus/__init__.py
wawpybus/analyse.py
wawpybus/collect.py
wawpybus/process.py
wawpybus-0.0.6.dist-info/LICENSE
wawpybus-0.0.6.dist-info/METADATA
wawpybus-0.0.6.dist-info/WHEEL
wawpybus-0.0.6.dist-info/top_level.txt
wawpybus-0.0.6.dist-info/RECORD
