Metadata-Version: 2.1
Name: wawpybus
Version: 0.0.6
Summary: A package providing tools to collect and analyse Warsaw open bus data
Home-page: https://gitlab.uw.edu.pl/ig386329/pybus
Author: Iwona Goździewska
Author-email: i.gozdziewska@students.mimuw.edu.pl
License: UNKNOWN
Platform: UNKNOWN
Classifier: Programming Language :: Python :: 3
Classifier: License :: OSI Approved :: MIT License
Classifier: Operating System :: OS Independent
Requires-Dist: requests
Requires-Dist: geopy
Requires-Dist: pandas
Requires-Dist: pytest
